Workbook

Sheet WEEK 30-6-25 TO 5-7-25
A1: WEEK 30-6-25 TO 5-7-25
C2: =SUM(C4:C18) -> 721610 | D2: =SUM(D4:D18) -> 557430 | E2: =ABS(C2-D2) -> 164180
A3: DATE | B3: DETAILS | C3: AMOUNT | D3: PAID | E3: BALANCE
B4: CRUSHING 3067.34 | C4: =ROUND(3067.34*220,-1) -> 674810 | D4: 0 | E4: =C4-D5 -> 674810
B5: R.STONE LOADING 57.68*15 | C5: =ROUND(57.68*15,-1) -> 870 | D5: 0 | E5: =IF(AND(C5="",D5=""),"",ABS(E4+C5-D5)) -> 675680
B6: 7500 FREIGHT CHARGE (121.33*270) | C6: =ROUND(121.33*270,-1) -> 32760 | D6: 0 | E6: =IF(AND(C6="",D6=""),"",ABS(E5+C6-D6)) -> 708440
B7: R.STONE SALES 57.68* | C7: 11100 | D7: 0 | E7: =IF(AND(C7="",D7=""),"",ABS(E23+C7-D7)) -> 712980
A8: 30/6/25 | B8: CASH | C8: 0 | D8: 50000 | E8: =IF(AND(C8="",D8=""),"",ABS(E7+C8-D8)) -> 662980
A9: 45664 | B9: CASH | C9: 0 | D9: 50000 | E9: =IF(AND(C9="",D9=""),"",ABS(E8+C9-D9)) -> 612980
A10: 45664 | B10: CASH | C10: 0 | D10: 10000 | E10: =IF(AND(C10="",D10=""),"",ABS(E9+C10-D10)) -> 602980
A11: 45695 | B11: G-PAY/PARTHIPAN | C11: 0 | D11: 100000 | E11: =IF(AND(C11="",D11=""),"",ABS(E10+C11-D11)) -> 502980
A12: 45695 | B12: CASH | C12: 0 | D12: 50000 | E12: =IF(AND(C12="",D12=""),"",ABS(E11+C12-D12)) -> 452980
A13: 45754 | B13: CASH | C13: 0 | D13: 28280 | E13: =IF(AND(C13="",D13=""),"",ABS(E12+C13-D13)) -> 424700
A14: 45784 | B14: CASH/RASAK | C14: 0 | D14: 18800 | E14: =IF(AND(C14="",D14=""),"",ABS(E13+C14-D14)) -> 405900
A15: 45784 | B15: CASH | C15: 0 | D15: 50350 | E15: =IF(AND(C15="",D15=""),"",ABS(E14+C15-D15)) -> 355550
A16: 0/0/25 | D16: 50000 | E16: =IF(AND(C16="",D16=""),"",ABS('WEEK 6-7-25 TO 12-7-25'!E6+C16-D16)) -> 41530
B17: GST | C17: 2070 | E17: =IF(AND(C17="",D17=""),"",ABS(E16+C17-D17)) -> 43600
D18: 150000 | E18: =IF(AND(C18="",D18=""),"",ABS(E16+C18-D18)) -> 108470
A19: TOTAL | C19: =C2 -> 721610 | D19: =D2 -> 557430 | E19: =E2 -> 164180
B23: WASTE LOADING 437.36*15 | C23: 0 | D23: =ROUND(437.36*15,-1) -> 6560 | E23: =IF(AND(C23="",D23=""),"",ABS(E6+C23-D23)) -> 701880

Sheet WEEK 6-7-25 TO 12-7-25
A1: WEEK 6-7-25 TO 12-7-25
C2: =SUM(C4:C20) -> 1213070 | D2: =SUM(D4:D20) -> 740710 | E2: =ABS(C2-D2) -> 472360
A3: DATE | B3: DETAILS | C3: AMOUNT | D3: PAID | E3: BALANCE
B4: OLD BALANCE | C4: ='WEEK 30-6-25 TO 5-7-25'!E2 -> 164180 | D4: 0 | E4: =C4-D4 -> 164180
A5: 45815 | B5: CASH | C5: 0 | D5: 100000 | E5: =IF(AND(C5="",D5=""),"",ABS(E4+C5-D5)) -> 64180
A6: 45815 | B6: CASH/AMAR/MATERIAL | C6: 0 | D6: 55710 | E6: =IF(AND(C6="",D6=""),"",ABS(E5+C6-D6)) -> 8470
B7: CRUSHING 4165.63 | C7: =ROUND(4165.63*220,-1) -> 916440 | D7: 0 | E7: =IF(AND(C7="",D7=""),"",ABS(E6+C7-D7)) -> 924910
B8: R.STONE LOADING 18.60*15 | C8: =ROUND(18.6*15,-1) -> 280 | D8: 0 | E8: =IF(AND(C8="",D8=""),"",ABS(E7+C8-D8)) -> 925190
B9: 7500 FREIGHT CHARGE (459.98*270) | C9: =ROUND(459.98*270,-1) -> 124190 | D9: 0 | E9: =IF(AND(C9="",D9=""),"",ABS(E8+C9-D9)) -> 1049380
B10: R.STONE SALES 18.60* | C10: 3580 | D10: 0 | E10: =IF(AND(C10="",D10=""),"",ABS(E9+C10-D10)) -> 1052960
A11: 45968 | B11: PARTHIPAN | C11: 0 | D11: 150000 | E11: =IF(AND(C11="",D11=""),"",ABS(E10+C11-D11)) -> 902960
A12: 45998 | B12: PARTHIPAN | C12: 0 | D12: 400000 | E12: =IF(AND(C12="",D12=""),"",ABS(E11+C12-D12)) -> 502960
C13: 0 | D13: 0 | E13: =IF(AND(C13="",D13=""),"",ABS(E12+C13-D13)) -> 502960
C14: 0 | D14: 0 | E14: =IF(AND(C14="",D14=""),"",ABS(E13+C14-D14)) -> 502960
C15: 0 | D15: 35000 | E15: =IF(AND(C15="",D15=""),"",ABS(E14+C15-D15)) -> 467960
B16: GST | C16: 4400 | D16: 0 | E16: =IF(AND(C16="",D16=""),"",ABS(E15+C16-D16)) -> 472360
E17: =IF(AND(C17="",D17=""),"",ABS(E16+C17-D17))
E18: =IF(AND(C18="",D18=""),"",ABS(E17+C18-D18))
E19: =IF(AND(C19="",D19=""),"",ABS(E18+C19-D19))
E20: =IF(AND(C20="",D20=""),"",ABS(E19+C20-D20))
A21: TOTAL | C21: =C2 -> 1213070 | D21: =D2 -> 740710 | E21: =E2 -> 472360

Sheet WEEK 13-7-25 TO 19-7-25
A1: WEEK 13-7-25 TO 19-7-25
C2: =SUM(C4:C22) -> 1398990 | D2: =SUM(D4:D22) -> 1147470 | E2: =ABS(C2-D2) -> 251520
A3: DATE | B3: DETAILS | C3: AMOUNT | D3: PAID | E3: BALANCE
B4: OLD BALANCE | C4: ='WEEK 6-7-25 TO 12-7-25'!E2 -> 472360 | D4: 0 | E4: =C4-D4 -> 472360
A5: 13/7/2025 | B5: CASH/AMAR/MATERIAL | C5: 0 | D5: 51740 | E5: =IF(AND(C5="",D5=""),"",ABS(E4+C5-D5)) -> 420620
A6: 14/7/2025 | B6: CASH/VIJAY | C6: 0 | D6: 23700 | E6: =IF(AND(C6="",D6=""),"",ABS(E5+C6-D6)) -> 396920
A7: 14/7/25 | B7: PARTHIPAN/GPAY | C7: 0 | D7: 300000 | E7: =IF(AND(C7="",D7=""),"",ABS(E6+C7-D7)) -> 96920
A8: 14/7/25 | B8: CASH/CREDIT SALES | C8: 0 | D8: 60000 | E8: =IF(AND(C8="",D8=""),"",ABS(E7+C8-D8)) -> 36920
A9: 14/7/25 | B9: CASH/CASH SALES | C9: 0 | D9: 40000 | E9: =IF(AND(C9="",D9=""),"",ABS(E8+C9-D9)) -> 3080
B10: ADVANCE | C10: 0 | D10: 3080 | E10: 0
E11: 0
B12: CRUSHING 3577.65 | C12: =ROUND(3577.65*220,-1) -> 787080 | D12: 0 | E12: =IF(AND(C12="",D12=""),"",ABS(E11+C12-D12)) -> 787080
B13: R.STONE LOADING 18.60*15 | C13: =ROUND(149.99*15,-1) -> 2250 | D13: 0 | E13: =IF(AND(C13="",D13=""),"",ABS(E12+C13-D13)) -> 789330
B14: 7500 FREIGHT CHARGE (459.98*270) | C14: =ROUND(401.59*270,-1) -> 108430 | D14: 0 | E14: =IF(AND(C14="",D14=""),"",ABS(E13+C14-D14)) -> 897760
B15: R.STONE SALES 149.99* | C15: 28870 | D15: 0 | E15: =IF(AND(C15="",D15=""),"",ABS(E14+C15-D15)) -> 926630
B16: WASTE LOADING | C16: 0 | D16: 840 | E16: =IF(AND(C16="",D16=""),"",ABS(E15+C16-D16)) -> 925790
A17: 19/7/25 | B17: CASH/KANNAN/MATERIAL | C17: 0 | D17: =344070-750 -> 343320 | E17: =IF(AND(C17="",D17=""),"",ABS(E16+C17-D17)) -> 582470
A18: 17/7/25 | B18: CASH | C18: 0 | D18: 16060 | E18: =IF(AND(C18="",D18=""),"",ABS(E17+C18-D18)) -> 566410
A19: 18/7/25 | B19: CASH | C19: 0 | D19: 8730 | E19: =IF(AND(C19="",D19=""),"",ABS(E18+C19-D19)) -> 557680
A20: 19/7/25 | B20: CASH | C20: 0 | D20: 50000 | E20: =IF(AND(C20="",D20=""),"",ABS(E19+C20-D20)) -> 507680
A21: 19/7/25 | B21: GPAY/BRUCE | C21: 0 | D21: 250000 | E21: =IF(AND(C21="",D21=""),"",ABS(E20+C21-D21)) -> 257680
E22: =IF(AND(C22="",D22=""),"",ABS(#REF!+C22-D22))
A23: TOTAL | C23: =C2 -> 1398990 | D23: =D2 -> 1147470 | E23: =E2 -> 251520

Sheet WEEK 20-7-25 TO 26-7-25
A1: WEEK 20-7-25 TO 26-7-25
C2: =SUM(C4:C18) -> 1038730 | D2: =SUM(D4:D18) -> 458190 | E2: =ABS(C2-D2) -> 580540
A3: DATE | B3: DETAILS | C3: AMOUNT | D3: PAID | E3: BALANCE
B4: OLD BALANCE | C4: ='WEEK 13-7-25 TO 19-7-25'!E21 -> 257680 | D4: 0 | E4: =C4-D4 -> 257680
A5: 21/7/25 | B5: GPAY/BRUCE | C5: 0 | D5: 57720 | E5: =IF(AND(C5="",D5=""),"",ABS(E4+C5-D5)) -> 199960
A6: 21/7/25 | B6: CASH/crediT SALES | C6: 0 | D6: 145200 | E6: =IF(AND(C6="",D6=""),"",ABS(E5+C6-D6)) -> 54760
A7: 21/7/25 | B7: CASH/CASH SALES | C7: 0 | D7: 54800 | E7: =IF(AND(C7="",D7=""),"",ABS(E6+C7-D7)) -> 40
B8: ADVANCE | C8: 0 | D8: 0 | E8: =IF(AND(C8="",D8=""),"",ABS(E7+C8-D8)) -> 40
D9: 0 | E9: 0
B10: CRUSHING 3515.36.65 | C10: =ROUND(3515.36*220,-1) -> 773380 | D10: 0 | E10: =IF(AND(C10="",D10=""),"",ABS(E9+C10-D10)) -> 773380
B11: R.STONE LOADING 40.34*15 | C11: =ROUND(40.34*15,-1) -> 610 | D11: 0 | E11: =IF(AND(C11="",D11=""),"",ABS(E10+C11-D11)) -> 773990
B12: R.STONE SALES 40.34*__ | C12: 7060 | D12: 0 | E12: =IF(AND(C12="",D12=""),"",ABS(E11+C12-D12)) -> 781050
B13: WASTE LOADING | C13: 0 | D13: 4400 | E13: =IF(AND(C13="",D13=""),"",ABS(E12+C13-D13)) -> 776650
A14: 19/7/25 | B14: RASAK/CASH | C14: 0 | D14: 21500 | E14: =IF(AND(C14="",D14=""),"",ABS(E13+C14-D14)) -> 755150
A15: 26/7/25 | B15: RAJKUMAR/BULK | C15: 0 | D15: 5000 | E15: =IF(AND(C15="",D15=""),"",ABS(E14+C15-D15)) -> 750150
A16: 26/7/25 | B16: CASH/SUGUMARAN | C16: 0 | D16: 14810 | E16: =IF(AND(C16="",D16=""),"",ABS(E15+C16-D16)) -> 735340
A17: 26/7/25 | B17: KANNAN/MATERIAL | C17: 0 | D17: 54760 | E17: =IF(AND(C17="",D17=""),"",ABS(E16+C17-D17)) -> 680580
A18: 26/7/25 | B18: BRUCE | C18: 0 | D18: 100000 | E18: =IF(AND(C18="",D18=""),"",ABS(E17+C18-D18)) -> 580580

Sheet WEEK 27-7-25 TO 2-8-25
A1: WEEK 27-7-25 TO 2-8-25
C2: =SUM(C4:C16) -> 580580 | D2: =SUM(D4:D16) -> 580580 | E2: =ABS(C2-D2) -> 0
A3: DATE | B3: DETAILS | C3: AMOUNT | D3: PAID | E3: BALANCE
B4: OLD BALANCE | C4: ='WEEK 20-7-25 TO 26-7-25'!E18 -> 580580 | D4: 0 | E4: =C4-D4 -> 580580
A5: 28/7/25 | B5: CASH/CASH SALES | C5: 0 | D5: 100000 | E5: =IF(AND(C5="",D5=""),"",ABS(E4+C5-D5)) -> 480580
A6: 28/7/25 | B6: CASH/SALES/ NARAYANAN | C6: 0 | D6: 16100 | E6: =IF(AND(C6="",D6=""),"",ABS(E5+C6-D6)) -> 464480
A7: 28/7/25 | B7: CASH/CREDIT SALES | C7: 0 | D7: 50400 | E7: =IF(AND(C7="",D7=""),"",ABS(E6+C7-D7)) -> 414080
A8: 28/7/25 | B8: CASH/CASH SALES | C8: 0 | D8: 33500 | E8: =IF(AND(C8="",D8=""),"",ABS(E7+C8-D8)) -> 380580
A9: 29/7/25 | B9: CASH/CASH SALES | C9: 0 | D9: 1130 | E9: =IF(AND(C9="",D9=""),"",ABS(E8+C9-D9)) -> 379450
A10: 30/7/25 | B10: GPAY/BRUCE | C10: 0 | D10: 100000 | E10: =IF(AND(C10="",D10=""),"",ABS(E9+C10-D10)) -> 279450
A11: 30/7/25 | B11: CASH/CASH SALES | C11: 0 | D11: 50000 | E11: =IF(AND(C11="",D11=""),"",ABS(E10+C11-D11)) -> 229450
A12: 31/7/25 | B12: CASH/CASH SALES | C12: 0 | D12: 40000 | E12: =IF(AND(C12="",D12=""),"",ABS(E11+C12-D12)) -> 189450
A13: 31/7/25 | B13: CASH/CASH SALES | C13: 0 | D13: 50000 | E13: =IF(AND(C13="",D13=""),"",ABS(E12+C13-D13)) -> 139450
A14: 45665 | B14: CASH/CASH SALES | C14: 0 | D14: 50000 | E14: =IF(AND(C14="",D14=""),"",ABS(E13+C14-D14)) -> 89450
A15: 45665 | B15: CASH/CASH SALES | C15: 0 | D15: 25000 | E15: =IF(AND(C15="",D15=""),"",ABS(E14+C15-D15)) -> 64450
A16: 45696 | B16: CASH/CASH SALES | C16: 0 | D16: 64450 | E16: =IF(AND(C16="",D16=""),"",ABS(E15+C16-D16)) -> 0
E17: 0
B18: CRUSHING 4133.24*220 | C18: =ROUND(4133.24*220,-1) -> 909310 | D18: 0 | E18: =IF(AND(C18="",D18=""),"",ABS(E17+C18-D18)) -> 909310
B19: 7500 FREIGHT CHARGE (278.75*270) | C19: =ROUND(278.75*270,-1) -> 75260 | D19: 0 | E19: =IF(AND(C19="",D19=""),"",ABS(E18+C19-D19)) -> 984570
B20: MISSING LOAD ON (16/7/25) 7500 FREIGHT CHARGE (30.53*270) | C20: =ROUND(30.53*270,-1) -> 8240 | D20: 0 | E20: =IF(AND(C20="",D20=""),"",ABS(E19+C20-D20)) -> 992810
B21: R.STONE LOADING 149.88*15 | C21: =ROUND(149.88*15,-1) -> 2250 | D21: 0 | E21: =IF(AND(C21="",D21=""),"",ABS(E20+C21-D21)) -> 995060
B22: R.STONE SALES 149.88*125 | C22: =ROUND(149.88*175,-1) -> 26230 | D22: 0 | E22: =IF(AND(C22="",D22=""),"",ABS(E21+C22-D22)) -> 1021290
B23: WASTE LOADING 493.60*15 | C23: 0 | D23: =ROUND(493.6*15,-1) -> 7400 | E23: =IF(AND(C23="",D23=""),"",ABS(E22+C23-D23)) -> 1013890
B24: CRUSHING 30.53*220 | C24: =ROUND(30.53*220,-1) -> 6720 | D24: 0 | E24: =IF(AND(C24="",D24=""),"",ABS(E23+C24-D24)) -> 1020610
A25: 45695 | B25: KANNAN/MATERIAL | C25: 0 | D25: 185460 | E25: =IF(AND(C25="",D25=""),"",ABS(E24+C25-D25)) -> 835150
